otpy/OTPY.py
otpy/__init__.py
otpy/__main__.py
otpy-0.0.2.dist-info/LICENSE
otpy-0.0.2.dist-info/METADATA
otpy-0.0.2.dist-info/WHEEL
otpy-0.0.2.dist-info/top_level.txt
otpy-0.0.2.dist-info/RECORD
